pkm-0.4.60.dist-info/WHEEL
pkm-0.4.60.dist-info/METADATA
pkm-0.4.60.dist-info/LICENSE
pkm-0.4.60.dist-info/entry_points.txt
pkm/.gitignore
pkm/__init__.py
pkm/launchers/t64-arm.exe
pkm/launchers/__init__.py
pkm/launchers/w32.exe
pkm/launchers/t64.exe
pkm/launchers/t32.exe
pkm/launchers/w64.exe
pkm/launchers/w64-arm.exe
pkm/resources/default_pkm_repositories.toml
pkm/resources/__init__.py
pkm/resources/default_pkm_general.toml
pkm/config/configclass.py
pkm/config/__init__.py
pkm/config/configfiles.py
pkm/config/toml.py
pkm/repositories/file_system_repository.py
pkm/repositories/url_repository.py
pkm/repositories/__init__.py
pkm/repositories/pypi_repository.py
pkm/repositories/git_repository.py
pkm/repositories/simple_repository.py
pkm/repositories/shared_pacakges_repo.py
pkm/repositories/file_repository.py
pkm/distributions/source_build_cache.py
pkm/distributions/__init__.py
pkm/distributions/executables.py
pkm/resolution/pubgrub.py
pkm/resolution/packages_lock.py
pkm/resolution/__init__.py
pkm/resolution/resolution_monitor.py
pkm/resolution/dependency_resolver.py
pkm/api/__init__.py
pkm/api/pkm.py
pkm/api/buildsys.py
pkm/api/licenses.py
pkm/api/versions/version_specifiers.py
pkm/api/versions/version.py
pkm/api/versions/__init__.py
pkm/api/versions/version_parser.py
pkm/api/packages/package_monitors.py
pkm/api/packages/site_packages.py
pkm/api/packages/package_installation.py
pkm/api/packages/package_installation_info.py
pkm/api/packages/package.py
pkm/api/packages/__init__.py
pkm/api/packages/package_metadata.py
pkm/api/packages/standard_package.py
pkm/api/projects/pyproject_configuration.py
pkm/api/projects/project_group.py
pkm/api/projects/environments_config.py
pkm/api/projects/project.py
pkm/api/projects/__init__.py
pkm/api/projects/project_monitors.py
pkm/api/repositories/repositories_configuration.py
pkm/api/repositories/repository_management.py
pkm/api/repositories/__init__.py
pkm/api/repositories/repository.py
pkm/api/repositories/repository_loader.py
pkm/api/distributions/pth_link.py
