Metadata-Version: 2.1
Name: pkm
Version: 0.4.60
Summary: Package Manager For Python
Requires-Python: >=3.8, <4.0
Author: bennyl
Author-email:
Maintainer: bennyl
Maintainer-email:
License: MIT License
